donb_custom_widget/__init__.py
donb_custom_widget/_pyinstaller_hook_dir.py
donb_custom_widget/hook-donb_custom_widget.py
donb_custom_widget/my_custom_widget.py
donb_custom_widget/py.typed
donb_custom_widget/data/ui_files/my_msg_box.ui
donb_custom_widget-1.1.1.dist-info/METADATA
donb_custom_widget-1.1.1.dist-info/WHEEL
donb_custom_widget-1.1.1.dist-info/entry_points.txt
donb_custom_widget-1.1.1.dist-info/top_level.txt
donb_custom_widget-1.1.1.dist-info/RECORD
