Metadata-Version: 2.1
Name: donb-custom-widget
Version: 1.1.1
Summary: Custom widget for Pyside6
Home-page: UNKNOWN
Author: Don Beberto
Author-email: bebert64@gmail.com
License: UNKNOWN
Platform: UNKNOWN
Requires-Dist: Pyside6
Requires-Dist: donb-tools
